jpaccident.py
jpaccident-0.0.2.dist-info/METADATA
jpaccident-0.0.2.dist-info/WHEEL
jpaccident-0.0.2.dist-info/entry_points.txt
jpaccident-0.0.2.dist-info/top_level.txt
jpaccident-0.0.2.dist-info/RECORD
