Metadata-Version: 2.1
Name: jpaccident
Version: 0.0.2
Summary: Package for visualization of aggregate data on fatalities in traffic accidents
Home-page: https://github.com/s2022027/jpaccident
Author: Tsuyoshi Hine
Author-email: tsuyoshi.h0920@gmail.com
License: UNKNOWN
Project-URL: Bug Tracker, https://github.com/s2022027/jpaccident
Platform: UNKNOWN
Classifier: Programming Language :: Python :: 3
Classifier: License :: OSI Approved :: MIT License
Classifier: Operating System :: OS Independent
Requires-Python: >=3.7
